Metadata-Version: 1.0
Name: xxtrace
Version: 3.2
Summary: xtrace wrap for XtraceMonitor
Home-page: http://github.com/wjx0912
Author: yongjian
Author-email: 80101277@qq.com
License: MIT
Platform: UNKNOWN
